{
  "NTA/WE48-P01": {
    "name": "力を緩めて なのは",
    "product_name": "PRカード【Wサイド】",
    "type": "角色卡",
    "level": 0,
    "power": 1500,
    "cost": 0,
    "trait": ["魔法", "武器"],
    "color": "红色",
    "soul": 1,
    "effect": "【永】 他のあなたの、《魔法》か《武器》のキャラがいるなら、このカードのパワーを＋1500。<br/>【自】 相手のアタックフェイズの始めに、このカードの正面に相手のキャラがいるなら、あなたはこのカードを前列のキャラのいない枠に動かしてよい。",
    "all_cards": [
      {
        "id": "NTA/WE48-P01",
        "rarity": "PR"
      },
      {
        "id": "NTA/WE48-P01EX",
        "rarity": "PR+"
      },
      {
        "id": "NTA/WE48-P01S",
        "rarity": "PR"
      }
    ]
  },
  "NTA/WE48-P02": {
    "name": "これからのこと フェイト",
    "product_name": "PRカード【Wサイド】",
    "type": "角色卡",
    "level": 0,
    "power": 1000,
    "cost": 0,
    "trait": ["魔法", "クローン"],
    "color": "黄色",
    "soul": 1,
    "effect": "【永】 他のあなたのカード名に「なのは」を含むキャラすべてに、『【自】 アンコール ［手札のキャラを1枚控え室に置く］』を与える。<br/>【自】［(1)］ このカードが手札から舞台に置かれた時、あなたはコストを払ってよい。そうしたら、あなたは自分のキャラを1枚選び、そのターン中、ソウルを＋1。",
    "all_cards": [
      {
        "id": "NTA/WE48-P02EX",
        "rarity": "PR+"
      },
      {
        "id": "NTA/WE48-P02S",
        "rarity": "PR"
      }
    ]
  },
  "NTA/WE48-P03": {
    "name": "願った時間 フェイト＆なのは",
    "product_name": "PRカード【Wサイド】",
    "type": "角色卡",
    "level": 0,
    "power": 1500,
    "cost": 0,
    "trait": ["魔法", "クローン"],
    "color": "黄色",
    "soul": 1,
    "effect": "【起】［(1) このカードを思い出にする］ あなたは自分の山札を上から4枚まで見て、《魔法》か《クローン》のキャラを1枚まで選んで相手に見せ、手札に加え、残りのカードを控え室に置く。",
    "all_cards": [
      {
        "id": "NTA/WE48-P03S",
        "rarity": "PR"
      }
    ]
  }
}
