{
  "KW/W11-102": {
    "name": "つばさをもった女の子 クド",
    "product_name": "2010年度トライアルデッキ【W】",
    "type": "角色卡",
    "level": 2,
    "power": 8000,
    "cost": 1,
    "rarity": [
      "TD"
    ],
    "trait": [
      "動物",
      "科学"
    ],
    "color": "蓝色",
    "soul": 1,
    "link": [],
    "effect": "【起】［あなたのキャラを2枚【レスト】する］ 次の相手のターンの終わりまで、このカードのパワーを＋1000。"
  },
  "KW/W11-105": {
    "name": "“ふらんくり～”クド",
    "product_name": "2010年度トライアルデッキ【W】",
    "type": "角色卡",
    "level": 0,
    "power": 1000,
    "cost": 0,
    "rarity": [
      "TD"
    ],
    "trait": [
      "動物",
      "科学"
    ],
    "color": "蓝色",
    "soul": 1,
    "link": [],
    "effect": "【永】 応援 このカードの前のあなたのキャラすべてに、パワーを＋500。"
  },
  "KW/W11-T08": {
    "name": "科学部の部長 氷室",
    "product_name": "2010年度トライアルデッキ【W】",
    "type": "角色卡",
    "level": 0,
    "power": 2500,
    "cost": 0,
    "rarity": [
      "TD"
    ],
    "trait": [
      "動物",
      "科学"
    ],
    "color": "蓝色",
    "soul": 1,
    "link": [],
    "effect": "【起】［あなたのキャラを2枚【レスト】する］ 次の相手のターンの終わりまで、このカードのパワーを＋１000。"
  },
  "KW/W11-T09": {
    "name": "家庭科部の部長 あーちゃん先輩",
    "product_name": "2010年度トライアルデッキ【W】",
    "type": "角色卡",
    "level": 1,
    "power": 4500,
    "cost": 0,
    "rarity": [
      "TD"
    ],
    "trait": [
      "動物"
    ],
    "color": "蓝色",
    "soul": 1,
    "link": [
      "KW/W11-T12",
      "KW/W11-094"
    ],
    "effect": "【自】 チェンジ ［(2) 手札を1枚控え室に置き、このカードを思い出にする］ あなたのアンコールステップの始めに、このカードが【レスト】しているなら、あなたはコストを払ってよい。そうしたら、あなたは自分の控え室の「ご隠居 あーちゃん先輩」を1枚選び、このカードがいた枠に置く。"
  },
  "KW/W11-T10": {
    "name": "湯上り 氷室",
    "product_name": "2010年度トライアルデッキ【W】",
    "type": "角色卡",
    "level": 1,
    "power": 7000,
    "cost": 1,
    "rarity": [
      "TD"
    ],
    "trait": [
      "動物",
      "科学"
    ],
    "color": "蓝色",
    "soul": 1,
    "link": [],
    "effect": "-"
  },
  "KW/W11-T11": {
    "name": "お買いもの クド",
    "product_name": "2010年度トライアルデッキ【W】",
    "type": "角色卡",
    "level": 2,
    "power": 7000,
    "cost": 2,
    "rarity": [
      "TD"
    ],
    "trait": [
      "動物",
      "科学"
    ],
    "color": "蓝色",
    "soul": 2,
    "link": [],
    "effect": "【自】 アンコール ［手札のキャラを1枚控え室に置く］ （このカードが舞台から控え室に置かれた時、あなたはコストを払ってよい。そうしたら、このカードがいた枠に【レスト】して置く）<br/>【起】［(1)］ そのターン中、このカードはサイドアタックしてもソウルが減少しない。"
  },
  "KW/W11-T12": {
    "name": "ご隠居 あーちゃん先輩",
    "product_name": "2010年度トライアルデッキ【W】",
    "type": "角色卡",
    "level": 2,
    "power": 9000,
    "cost": 2,
    "rarity": [
      "TD"
    ],
    "trait": [
      "動物",
      "お茶"
    ],
    "color": "蓝色",
    "soul": 2,
    "link": [
      "KW/W11-T09",
      "KW/W11-086"
    ],
    "effect": "-"
  },
  "KW/W11-T13": {
    "name": "プールサイドの遭遇",
    "product_name": "2010年度トライアルデッキ【W】",
    "type": "高潮卡",
    "level": "-",
    "power": "-",
    "cost": "-",
    "rarity": [
      "TD"
    ],
    "trait": "-",
    "color": "蓝色",
    "soul": "-",
    "link": [
      "KW/W11-081"
    ],
    "effect": "【自】 このカードが手札からクライマックス置場に置かれた時、あなたは1枚引き、自分のキャラを1枚選び、そのターン中、パワーを＋2000し、ソウルを＋1。"
  },
  "KW/W11-T14": {
    "name": "えきぞちっくな誓い",
    "product_name": "2010年度トライアルデッキ【W】",
    "type": "高潮卡",
    "level": "-",
    "power": "-",
    "cost": "-",
    "rarity": [
      "TD"
    ],
    "trait": "-",
    "color": "蓝色",
    "soul": "-",
    "link": [
      "KW/W11-080"
    ],
    "effect": "【永】 あなたのキャラすべてに、パワーを＋1000し、ソウルを＋1。<br/>（<img src=\"/wordpress/wp-content/images/cardlist/_partimages/draw.gif\"/>：このカードがトリガーした時、あなたは1枚引いてよい）"
  }
}